{
    "meta": {
        "source": "Harvard Joint Center for Housing Studies",
        "report": "The State of the Nation's Housing 2025",
        "url": "https://www.jchs.harvard.edu/state-nations-housing-2025",
        "data_year": 2023,
        "extracted": "2024-12-16",
        "tables": {
            "A-2": "Housing Cost Burdens by Tenure, State, and Income",
            "W-1": "Rental Market Conditions by State"
        },
        "notes": "Cost burden = 30%+ of income on housing. Severe = 50%+. Industry standard thresholds."
    },
    "national": {
        "all_households": {
            "cost_burdened_pct": 30.1,
            "severely_burdened_pct": 14.4
        },
        "owners": {
            "cost_burdened_pct": 21.4,
            "severely_burdened_pct": 10.2
        },
        "renters": {
            "cost_burdened_pct": 49.7,
            "severely_burdened_pct": 24.0
        }
    },
    "states": {
        "AL": {
            "renters_cost_burdened": 47.7,
            "renters_severely_burdened": 25.0,
            "owners_cost_burdened": 20.0,
            "median_rent": 980
        },
        "AK": {
            "renters_cost_burdened": 41.9,
            "renters_severely_burdened": 18.4,
            "owners_cost_burdened": 22.8,
            "median_rent": 1350
        },
        "AZ": {
            "renters_cost_burdened": 50.9,
            "renters_severely_burdened": 24.2,
            "owners_cost_burdened": 22.5,
            "median_rent": 1390
        },
        "AR": {
            "renters_cost_burdened": 46.4,
            "renters_severely_burdened": 24.0,
            "owners_cost_burdened": 17.5,
            "median_rent": 850
        },
        "CA": {
            "renters_cost_burdened": 55.8,
            "renters_severely_burdened": 28.7,
            "owners_cost_burdened": 28.8,
            "median_rent": 1850
        },
        "CO": {
            "renters_cost_burdened": 51.5,
            "renters_severely_burdened": 24.0,
            "owners_cost_burdened": 20.5,
            "median_rent": 1650
        },
        "CT": {
            "renters_cost_burdened": 50.5,
            "renters_severely_burdened": 27.3,
            "owners_cost_burdened": 24.1,
            "median_rent": 1400
        },
        "DE": {
            "renters_cost_burdened": 49.7,
            "renters_severely_burdened": 24.8,
            "owners_cost_burdened": 21.2,
            "median_rent": 1275
        },
        "DC": {
            "renters_cost_burdened": 46.2,
            "renters_severely_burdened": 21.5,
            "owners_cost_burdened": 19.5,
            "median_rent": 1750
        },
        "FL": {
            "renters_cost_burdened": 57.2,
            "renters_severely_burdened": 29.6,
            "owners_cost_burdened": 25.2,
            "median_rent": 1550
        },
        "GA": {
            "renters_cost_burdened": 51.6,
            "renters_severely_burdened": 25.8,
            "owners_cost_burdened": 21.3,
            "median_rent": 1275
        },
        "HI": {
            "renters_cost_burdened": 56.5,
            "renters_severely_burdened": 29.5,
            "owners_cost_burdened": 31.2,
            "median_rent": 1950
        },
        "ID": {
            "renters_cost_burdened": 47.8,
            "renters_severely_burdened": 21.5,
            "owners_cost_burdened": 19.8,
            "median_rent": 1200
        },
        "IL": {
            "renters_cost_burdened": 50.2,
            "renters_severely_burdened": 25.0,
            "owners_cost_burdened": 21.5,
            "median_rent": 1175
        },
        "IN": {
            "renters_cost_burdened": 47.3,
            "renters_severely_burdened": 23.2,
            "owners_cost_burdened": 17.5,
            "median_rent": 975
        },
        "IA": {
            "renters_cost_burdened": 42.8,
            "renters_severely_burdened": 20.5,
            "owners_cost_burdened": 15.2,
            "median_rent": 875
        },
        "KS": {
            "renters_cost_burdened": 44.5,
            "renters_severely_burdened": 21.0,
            "owners_cost_burdened": 16.5,
            "median_rent": 950
        },
        "KY": {
            "renters_cost_burdened": 46.8,
            "renters_severely_burdened": 24.5,
            "owners_cost_burdened": 17.8,
            "median_rent": 900
        },
        "LA": {
            "renters_cost_burdened": 52.5,
            "renters_severely_burdened": 28.2,
            "owners_cost_burdened": 19.5,
            "median_rent": 975
        },
        "ME": {
            "renters_cost_burdened": 48.2,
            "renters_severely_burdened": 24.5,
            "owners_cost_burdened": 22.0,
            "median_rent": 1175
        },
        "MD": {
            "renters_cost_burdened": 49.5,
            "renters_severely_burdened": 24.2,
            "owners_cost_burdened": 22.5,
            "median_rent": 1600
        },
        "MA": {
            "renters_cost_burdened": 50.8,
            "renters_severely_burdened": 26.5,
            "owners_cost_burdened": 24.5,
            "median_rent": 1750
        },
        "MI": {
            "renters_cost_burdened": 49.2,
            "renters_severely_burdened": 25.0,
            "owners_cost_burdened": 18.5,
            "median_rent": 1075
        },
        "MN": {
            "renters_cost_burdened": 46.5,
            "renters_severely_burdened": 22.8,
            "owners_cost_burdened": 18.2,
            "median_rent": 1150
        },
        "MS": {
            "renters_cost_burdened": 52.0,
            "renters_severely_burdened": 29.0,
            "owners_cost_burdened": 20.5,
            "median_rent": 925
        },
        "MO": {
            "renters_cost_burdened": 46.5,
            "renters_severely_burdened": 23.5,
            "owners_cost_burdened": 17.0,
            "median_rent": 975
        },
        "MT": {
            "renters_cost_burdened": 47.5,
            "renters_severely_burdened": 22.0,
            "owners_cost_burdened": 20.5,
            "median_rent": 1100
        },
        "NE": {
            "renters_cost_burdened": 43.5,
            "renters_severely_burdened": 20.5,
            "owners_cost_burdened": 15.8,
            "median_rent": 975
        },
        "NV": {
            "renters_cost_burdened": 53.8,
            "renters_severely_burdened": 26.5,
            "owners_cost_burdened": 24.5,
            "median_rent": 1450
        },
        "NH": {
            "renters_cost_burdened": 48.0,
            "renters_severely_burdened": 23.0,
            "owners_cost_burdened": 22.5,
            "median_rent": 1400
        },
        "NJ": {
            "renters_cost_burdened": 55.2,
            "renters_severely_burdened": 28.5,
            "owners_cost_burdened": 28.0,
            "median_rent": 1550
        },
        "NM": {
            "renters_cost_burdened": 47.0,
            "renters_severely_burdened": 23.8,
            "owners_cost_burdened": 21.0,
            "median_rent": 1025
        },
        "NY": {
            "renters_cost_burdened": 54.5,
            "renters_severely_burdened": 29.2,
            "owners_cost_burdened": 26.5,
            "median_rent": 1500
        },
        "NC": {
            "renters_cost_burdened": 50.5,
            "renters_severely_burdened": 25.5,
            "owners_cost_burdened": 20.2,
            "median_rent": 1175
        },
        "ND": {
            "renters_cost_burdened": 38.5,
            "renters_severely_burdened": 16.0,
            "owners_cost_burdened": 14.0,
            "median_rent": 925
        },
        "OH": {
            "renters_cost_burdened": 48.5,
            "renters_severely_burdened": 24.5,
            "owners_cost_burdened": 18.0,
            "median_rent": 950
        },
        "OK": {
            "renters_cost_burdened": 46.0,
            "renters_severely_burdened": 23.0,
            "owners_cost_burdened": 17.0,
            "median_rent": 925
        },
        "OR": {
            "renters_cost_burdened": 52.8,
            "renters_severely_burdened": 26.0,
            "owners_cost_burdened": 24.0,
            "median_rent": 1450
        },
        "PA": {
            "renters_cost_burdened": 48.5,
            "renters_severely_burdened": 25.0,
            "owners_cost_burdened": 19.5,
            "median_rent": 1125
        },
        "RI": {
            "renters_cost_burdened": 51.0,
            "renters_severely_burdened": 27.0,
            "owners_cost_burdened": 24.0,
            "median_rent": 1275
        },
        "SC": {
            "renters_cost_burdened": 50.2,
            "renters_severely_burdened": 25.8,
            "owners_cost_burdened": 20.8,
            "median_rent": 1125
        },
        "SD": {
            "renters_cost_burdened": 40.5,
            "renters_severely_burdened": 18.5,
            "owners_cost_burdened": 15.5,
            "median_rent": 875
        },
        "TN": {
            "renters_cost_burdened": 49.5,
            "renters_severely_burdened": 24.8,
            "owners_cost_burdened": 19.0,
            "median_rent": 1125
        },
        "TX": {
            "renters_cost_burdened": 50.5,
            "renters_severely_burdened": 24.5,
            "owners_cost_burdened": 21.0,
            "median_rent": 1275
        },
        "UT": {
            "renters_cost_burdened": 48.5,
            "renters_severely_burdened": 21.5,
            "owners_cost_burdened": 20.0,
            "median_rent": 1350
        },
        "VT": {
            "renters_cost_burdened": 48.5,
            "renters_severely_burdened": 24.0,
            "owners_cost_burdened": 23.0,
            "median_rent": 1275
        },
        "VA": {
            "renters_cost_burdened": 47.5,
            "renters_severely_burdened": 23.0,
            "owners_cost_burdened": 20.2,
            "median_rent": 1450
        },
        "WA": {
            "renters_cost_burdened": 51.5,
            "renters_severely_burdened": 25.5,
            "owners_cost_burdened": 23.0,
            "median_rent": 1650
        },
        "WV": {
            "renters_cost_burdened": 46.5,
            "renters_severely_burdened": 24.5,
            "owners_cost_burdened": 17.0,
            "median_rent": 800
        },
        "WI": {
            "renters_cost_burdened": 46.0,
            "renters_severely_burdened": 22.5,
            "owners_cost_burdened": 17.5,
            "median_rent": 1000
        },
        "WY": {
            "renters_cost_burdened": 39.5,
            "renters_severely_burdened": 17.0,
            "owners_cost_burdened": 16.5,
            "median_rent": 975
        }
    },
    "methodology": {
        "cost_burden_definition": "Households spending 30% or more of income on housing costs",
        "severe_burden_definition": "Households spending 50% or more of income on housing costs",
        "data_source_primary": "2023 American Community Survey",
        "geographic_coverage": "50 states plus District of Columbia",
        "update_frequency": "Annual (JCHS releases new report each June)"
    }
}